api_bridge/__init__.py
api_bridge/api.py
api_bridge/container.py
api_bridge/exceptions.py
api_bridge/filter.py
api_bridge/methods.py
api_bridge/url.py
api_bridge-0.0.7.dist-info/LICENSE
api_bridge-0.0.7.dist-info/METADATA
api_bridge-0.0.7.dist-info/WHEEL
api_bridge-0.0.7.dist-info/top_level.txt
api_bridge-0.0.7.dist-info/RECORD
