Metadata-Version: 2.1
Name: api-bridge
Version: 0.0.7
Summary: Joining json API calls together
Home-page: https://github.com/robin-weiland/APIBridge
Author: Robin 'r0w' Weiland
Author-email: robin.weiland@gmx.de
License: MIT
Keywords: api,json,web
Platform: UNKNOWN
Classifier: Development Status :: 5 - Production/Stable
Classifier: Intended Audience :: Developers
Classifier: Topic :: Software Development
Classifier: License :: OSI Approved :: MIT License
Classifier: Programming Language :: Python :: 3.6
Classifier: Operating System :: OS Independent
Requires: certifi
Requires: chardet
Requires: idna
Requires: requests
Requires: urllib3
Requires: setuptools
Requires-Python: >=3.6
